qogir/__init__.py
qogir/core/__init__.py
qogir/core/arunner.py
qogir/core/runner.py
qogir/core/commands/__init__.py
qogir/core/commands/createjob.py
qogir/core/commands/runjob.py
qogir/core/jobs/__init__.py
qogir/core/jobs/default.py
qogir/core/jobs/pyspark_.py
qogir/templates/check_venv.sh.tpl
qogir/templates/default.submit.sh.tpl
qogir/templates/pyspark.submit.sh.tpl
qogir/templates/default_job_template/.qogir.tpl
qogir/templates/default_job_template/__init__.py.tpl
qogir/templates/default_job_template/config.yaml
qogir/templates/default_job_template/config.yaml.tpl
qogir/templates/default_job_template/job.py.tpl
qogir/templates/default_job_template/requirements.txt
qogir/templates/pyspark_job_template/.qogir.tpl
qogir/templates/pyspark_job_template/__init__.py.tpl
qogir/templates/pyspark_job_template/config.yaml.tpl
qogir/templates/pyspark_job_template/job.py.tpl
qogir/templates/pyspark_job_template/requirements.txt
qogir/utils/__init__.py
qogir/utils/commands.py
qogir-2021.9.16.dist-info/METADATA
qogir-2021.9.16.dist-info/WHEEL
qogir-2021.9.16.dist-info/entry_points.txt
qogir-2021.9.16.dist-info/top_level.txt
qogir-2021.9.16.dist-info/RECORD
