Metadata-Version: 2.1
Name: qogir
Version: 2021.9.16
Summary: Qogir: Make task easier
Home-page: UNKNOWN
Author: Jerevia
Author-email: trilliondawn@gmail.com
License: MIT
Keywords: qogir spark
Platform: UNKNOWN
Classifier: Development Status :: 4 - Beta
Classifier: Intended Audience :: Developers
Classifier: Topic :: Software Development :: Build Tools
Classifier: License :: OSI Approved :: MIT License
Classifier: Programming Language :: Python :: 2.7
Classifier: Programming Language :: Python :: 3.4
Classifier: Programming Language :: Python :: 3.5
Classifier: Programming Language :: Python :: 3.6
Classifier: Programming Language :: Python :: 3.7
Classifier: Programming Language :: Python :: 3.8
Requires-Python: >=2.6
Requires-Dist: pyyaml
Provides-Extra: dev
Provides-Extra: test
